countertype_sp-0.1.2.dist-info/licenses/LICENSE
countertypes/__init__.py
countertype_sp-0.1.2.dist-info/METADATA
countertype_sp-0.1.2.dist-info/WHEEL
countertype_sp-0.1.2.dist-info/top_level.txt
countertype_sp-0.1.2.dist-info/RECORD
